qcompute_qsvt/__init__.py
qcompute_qsvt/Application/__init__.py
qcompute_qsvt/Application/HamiltonianSimulation/HamiltonianGenerator.py
qcompute_qsvt/Application/HamiltonianSimulation/HamiltonianSimulation.py
qcompute_qsvt/Application/HamiltonianSimulation/SymmetricQSPHS.py
qcompute_qsvt/Application/HamiltonianSimulation/__init__.py
qcompute_qsvt/Gate/MultiCtrlGates.py
qcompute_qsvt/Gate/__init__.py
qcompute_qsvt/Oracle/BlockEncoding.py
qcompute_qsvt/Oracle/StatePreparation.py
qcompute_qsvt/Oracle/__init__.py
qcompute_qsvt/QSVT/QSVT.py
qcompute_qsvt/QSVT/__init__.py
qcompute_qsvt/SymmetricQSP/Settings.py
qcompute_qsvt/SymmetricQSP/SymmetricQSPExternal.py
qcompute_qsvt/SymmetricQSP/SymmetricQSPInternalCpp.py
qcompute_qsvt/SymmetricQSP/SymmetricQSPInternalPy.py
qcompute_qsvt/SymmetricQSP/__init__.py
qcompute_qsvt/SymmetricQSP/arm/SymmetricQSPInternalCpp.cpython-39-darwin.so
qcompute_qsvt/SymmetricQSP/arm/__init__.py
qcompute_qsvt/SymmetricQSP/x64/SymmetricQSPInternalCpp.cp39-win_amd64.pyd
qcompute_qsvt/SymmetricQSP/x64/SymmetricQSPInternalCpp.cpython-39-darwin.so
qcompute_qsvt/SymmetricQSP/x64/SymmetricQSPInternalCpp.cpython-39-x86_64-linux-gnu.so
qcompute_qsvt/SymmetricQSP/x64/__init__.py
qcompute_qsvt/SymmetricQSP/x64/libiomp5md.dll
qcompute_qsvt/SymmetricQSP/x64/msvcp140.dll
qcompute_qsvt/SymmetricQSP/x64/vcruntime140.dll
qcompute_qsvt-0.1.1.dist-info/LICENSE
qcompute_qsvt-0.1.1.dist-info/METADATA
qcompute_qsvt-0.1.1.dist-info/WHEEL
qcompute_qsvt-0.1.1.dist-info/top_level.txt
qcompute_qsvt-0.1.1.dist-info/RECORD
