Metadata-Version: 2.1
Name: qcompute-qsvt
Version: 0.1.1
Summary: Quantum Singular Value Transformation toolkit developed by the Institute for Quantum Computing at Baidu Research.
Home-page: https://quantum.baidu.com
Author: Baidu Quantum
Author-email: quantum@baidu.com
License: Apache License 2.0
Requires-Python: >=3.9, <3.10
License-File: LICENSE
Requires-Dist: qcompute (==3.2.0)
